README.txt
setup.cfg
setup.py
collective/__init__.py
collective.googlemodifycontent.egg-info/PKG-INFO
collective.googlemodifycontent.egg-info/SOURCES.txt
collective.googlemodifycontent.egg-info/dependency_links.txt
collective.googlemodifycontent.egg-info/entry_points.txt
collective.googlemodifycontent.egg-info/namespace_packages.txt
collective.googlemodifycontent.egg-info/not-zip-safe
collective.googlemodifycontent.egg-info/requires.txt
collective.googlemodifycontent.egg-info/top_level.txt
collective/googlemodifycontent/LICENSE
collective/googlemodifycontent/__init__.py
collective/googlemodifycontent/configure.zcml
collective/googlemodifycontent/tests.py
collective/googlemodifycontent/browser/__init__.py
collective/googlemodifycontent/browser/configure.zcml
collective/googlemodifycontent/browser/googlemodifycontent.pt
collective/googlemodifycontent/browser/googlemodifycontent.py
collective/googlemodifycontent/profiles/default/actions.xml
collective/googlemodifycontent/profiles/default/metadata.xml
docs/HISTORY.txt
docs/INSTALL.txt
docs/LICENSE.GPL
docs/LICENSE.txt