Metadata-Version: 1.0
Name: collective.googlemodifycontent
Version: 1.0.0
Summary: GMC embeds the Google Docs application inside the Google Modify panel, allowing Plone users to edit their documents directly from the Plone application
Home-page: http://svn.plone.org/svn/collective/collective.googlemodifycontent
Author: D'Elia Federica
Author-email: federica.delia@redturtle.it
License: GPL
Keywords: plone google googledocs
Platform: UNKNOWN
Classifier: Framework :: Plone
Classifier: Programming Language :: Python
Classifier: Topic :: Software Development :: Libraries :: Python Modules
